xenia_generic/__init__.py
xenia_generic/col_tex.py
xenia_generic/id_generator.py
xenia_generic/object_to_str.py
xenia_generic/parameter_integrity_check.py
xenia_generic/strings_functions.py
xenia_generic-0.0.0.dist-info/LICENSE.txt
xenia_generic-0.0.0.dist-info/METADATA
xenia_generic-0.0.0.dist-info/WHEEL
xenia_generic-0.0.0.dist-info/top_level.txt
xenia_generic-0.0.0.dist-info/RECORD
