Metadata-Version: 2.1
Name: xenia-generic
Version: 0.0.0
Summary: Xenia Generic Utilities
Home-page: https://github.com/xenia2023/xenia_generic
Author: Stefano Gigli
Author-email: xenia-dev@programmer.net
License: UNKNOWN
Project-URL: Source, https://github.com/xenia2023/xenia_generic
Keywords: colored text,id generator,debugging,parameters check,strings functions
Platform: UNKNOWN
Classifier: Development Status :: 3 - Alpha
Classifier: Intended Audience :: Developers
Classifier: Topic :: Software Development :: Libraries
Classifier: License :: OSI Approved :: GNU General Public License v3 or later (GPLv3+)
Classifier: Programming Language :: Python :: 3
Classifier: Programming Language :: Python :: 3.6
Classifier: Programming Language :: Python :: 3.7
Classifier: Programming Language :: Python :: 3.8
Classifier: Programming Language :: Python :: 3.9
Classifier: Programming Language :: Python :: 3 :: Only
